buildstrap/__init__.py
buildstrap/buildstrap.py
buildstrap/templates/pytest.part.cfg
buildstrap/templates/sphinx.part.cfg
buildstrap-0.4.0.dist-info/DESCRIPTION.rst
buildstrap-0.4.0.dist-info/METADATA
buildstrap-0.4.0.dist-info/RECORD
buildstrap-0.4.0.dist-info/WHEEL
buildstrap-0.4.0.dist-info/entry_points.txt
buildstrap-0.4.0.dist-info/metadata.json
buildstrap-0.4.0.dist-info/top_level.txt
