Metadata-Version: 2.0
Name: buildstrap
Version: 0.4.0
Summary: Tool for managing remote repositories from your git CLI!
Home-page: https://github.com/guyzmo/buildstrap
Author: Bernard `Guyzmo` Pratz
Author-email: guyzmo+buildstrap+pub@m0g.net
License: WTFPL
Keywords: git
Platform: UNKNOWN
Classifier: Development Status :: 4 - Beta
Classifier: Programming Language :: Python :: 3
Classifier: Programming Language :: Python :: 3.4
Classifier: Programming Language :: Python :: 3.5
Classifier: Framework :: Buildout
Classifier: Environment :: Console
Classifier: Intended Audience :: Developers
Classifier: License :: Freely Distributable
Classifier: Topic :: Software Development
Classifier: Topic :: Software Development :: Build Tools
Classifier: Topic :: Utilities
Requires-Dist: docopt
Requires-Dist: zc.buildout
